.class public Exemplo7
.super java/lang/Object

.method public <init>()V
	aload_0

	invokenonvirtual java/lang/Object/<init>()V
	return
.end method

.method public static main([Ljava/lang/String;)V
	.limit stack 10
	.limit locals 4
	iconst_1
	istore 1
	iconst_0
	istore 3
	iconst_5
	istore 2
	getstatic java/lang/System/out Ljava/io/PrintStream;
	ldc "t ="
	invokevirtual java/io/PrintStream/println(Ljava/lang/String;)V
L1:
	getstatic java/lang/System/out Ljava/io/PrintStream;
	iload 3
	invokevirtual java/io/PrintStream/println(I)V
	iload 3
	iload 1
	iload 2
	imul
	iadd
	istore 3
	iload 1
	iconst_1
	iadd
	istore 1
	iload 3
	bipush 50
	if_icmple L1
	goto L2
L2:
	getstatic java/lang/System/out Ljava/io/PrintStream;
	ldc "Finish"
	invokevirtual java/io/PrintStream/println(Ljava/lang/String;)V
	getstatic java/lang/System/out Ljava/io/PrintStream;
	ldc "valor final de t:"
	invokevirtual java/io/PrintStream/println(Ljava/lang/String;)V
	getstatic java/lang/System/out Ljava/io/PrintStream;
	iload 3
	invokevirtual java/io/PrintStream/println(I)V
	return
.end method
